simplyfire/__init__.py
simplyfire/__main__.py
simplyfire/app.py
simplyfire/pyproject.toml
simplyfire/setup.cfg
simplyfire/__pycache__/__init__.cpython-311.pyc
simplyfire/__pycache__/__main__.cpython-311.pyc
simplyfire/__pycache__/app.cpython-311.pyc
simplyfire/backend/__init__.py
simplyfire/backend/interface.py
simplyfire/backend/interpreter.py
simplyfire/backend/plugin_manager.py
simplyfire/backend/__pycache__/__init__.cpython-311.pyc
simplyfire/backend/__pycache__/interface.cpython-311.pyc
simplyfire/backend/__pycache__/interpreter.cpython-311.pyc
simplyfire/backend/__pycache__/plugin_manager.cpython-311.pyc
simplyfire/img/arrow.png
simplyfire/img/loading.gif
simplyfire/img/logo.ico
simplyfire/img/logo_bw.ico
simplyfire/img/pan_up.png
simplyfire/img/x_zoom_in.png
simplyfire/img/x_zoom_out.png
simplyfire/img/y_zoom_in.png
simplyfire/img/y_zoom_out.png
simplyfire/img/zoom_in_y.png
simplyfire/layout/__init__.py
simplyfire/layout/batch_popup.py
simplyfire/layout/graph_panel.py
simplyfire/layout/log_display.py
simplyfire/layout/menubar.py
simplyfire/layout/plugin_tab.py
simplyfire/layout/results_display.py
simplyfire/layout/setting_tab.py
simplyfire/layout/trace_display.py
simplyfire/layout/__pycache__/__init__.cpython-311.pyc
simplyfire/layout/__pycache__/batch_popup.cpython-311.pyc
simplyfire/layout/__pycache__/graph_panel.cpython-311.pyc
simplyfire/layout/__pycache__/log_display.cpython-311.pyc
simplyfire/layout/__pycache__/menubar.cpython-311.pyc
simplyfire/layout/__pycache__/plugin_tab.cpython-311.pyc
simplyfire/layout/__pycache__/results_display.cpython-311.pyc
simplyfire/layout/__pycache__/setting_tab.cpython-311.pyc
simplyfire/layout/__pycache__/trace_display.cpython-311.pyc
simplyfire/plugins/comparison_plot/comparison_GUI.py
simplyfire/plugins/comparison_plot/plugin.yaml
simplyfire/plugins/comparison_plot/__pycache__/comparison_GUI.cpython-311.pyc
simplyfire/plugins/evoked_basic/evoked_GUI.py
simplyfire/plugins/evoked_basic/evoked_analysis.py
simplyfire-0.6.1.dist-info/LICENSE
simplyfire-0.6.1.dist-info/METADATA
simplyfire-0.6.1.dist-info/WHEEL
simplyfire-0.6.1.dist-info/entry_points.txt
simplyfire-0.6.1.dist-info/top_level.txt
simplyfire-0.6.1.dist-info/RECORD
