Metadata-Version: 2.1
Name: simplyfire
Version: 0.6.1
Summary: Customizable electrophysiology analysis software
Home-page: https://simplyfire.readthedocs.io/
Author: Megumi Mori, Andrew Rosko
License: GNU General Public License v3
Keywords: neuroscience,analysis,electrophysiology,gui-application
Classifier: Development Status :: 4 - Beta
Classifier: License :: OSI Approved :: GNU General Public License v3 (GPLv3)
Classifier: Natural Language :: English
Classifier: Programming Language :: Python :: 3
Classifier: Operating System :: Microsoft :: Windows
Requires-Python: >=3.8
License-File: LICENSE
Requires-Dist: numpy >=1.21.5
Requires-Dist: pandas >=1.3.5
Requires-Dist: matplotlib >=3.5.1
Requires-Dist: scipy >=1.7.3
Requires-Dist: pyyaml >=6.0
Requires-Dist: pyabf >=2.3.5
Requires-Dist: packaging
